no_more_imports-0.1.1.dist-info/METADATA
no_more_imports-0.1.1.dist-info/WHEEL
no_more_imports-0.1.1.dist-info/entry_points.txt
no_more_imports-0.1.1.dist-info/licenses/LICENSE
no_more_imports/__init__.py
no_more_imports/ast.py
no_more_imports/const.py
no_more_imports/importer.py
no_more_imports-0.1.1.dist-info/RECORD
