Metadata-Version: 2.1
Name: no-more-imports
Version: 0.1.1
Summary: python with no imports
Home-page: https://git.jon-e.net/jonny/no-more-imports
Author-Email: sneakers-the-rat <sneakers-the-rat@protonmail.com>
License: EUPL-1.2
Project-URL: Repository, https://git.jon-e.net/jonny/no-more-imports
Project-URL: Homepage, https://git.jon-e.net/jonny/no-more-imports
Project-URL: Issues, https://git.jon-e.net/jonny/no-more-imports
Project-URL: Documentation, https://git.jon-e.net/jonny/no-more-imports/src/branch/main/README.md
Requires-Python: >=3.10
Provides-Extra: tests
Requires-Dist: pytest>=8.3.3; extra == "tests"
Provides-Extra: dev
Requires-Dist: black>=24.10.0; extra == "dev"
Requires-Dist: ruff>=0.6.9; extra == "dev"
